secparse/__init__.py
secparse/client.py
secparse-0.1.1.dist-info/METADATA
secparse-0.1.1.dist-info/WHEEL
secparse-0.1.1.dist-info/top_level.txt
secparse-0.1.1.dist-info/RECORD
