Metadata-Version: 2.4
Name: secparse
Version: 0.1.1
Summary: SecParse API SDK for Python (secparse.com)
Author-email: Håkon Kleven <haakon@secparse.com>
License-Expression: MIT
Project-URL: Homepage, https://secparse.com
Project-URL: Documentation, https://github.com/PowerKuu/secparse-sdk#readme
Project-URL: Repository, https://github.com/PowerKuu/secparse-sdk
Project-URL: Bug Tracker, https://github.com/PowerKuu/secparse-sdk/issues
Keywords: secparse,graphql,sdk,client,subscriptions,websocket
Requires-Python: >=3.8
Requires-Dist: gql[all]>=4.0.0
